Metadata-Version: 2.4
Name: vsensebox-ultralytics
Version: 8.4.7
Summary: Ultralytics YOLO for SOTA object detection, multi-object tracking, instance segmentation, pose estimation and image classification.
Home-page: https://github.com/numediart/ultralytics-for-vsensebox
License: AGPL-3.0
Project-URL: Bug Reports, https://github.com/numediart/ultralytics-for-vsensebox/issues
Project-URL: Source, https://github.com/numediart/ultralytics-for-vsensebox
Keywords: machine-learning,deep-learning,computer-vision,ML,DL,AI,YOLO,YOLOv3,YOLOv5,YOLOv8,YOLOv9,YOLOv10,YOLO11,HUB,Ultralytics
Classifier: Development Status :: 4 - Beta
Classifier: Intended Audience :: Developers
Classifier: Intended Audience :: Education
Classifier: Intended Audience :: Science/Research
Classifier: License :: OSI Approved :: GNU Affero General Public License v3 or later (AGPLv3+)
Classifier: Programming Language :: Python :: 3
Classifier: Programming Language :: Python :: 3.8
Classifier: Programming Language :: Python :: 3.9
Classifier: Programming Language :: Python :: 3.10
Classifier: Programming Language :: Python :: 3.11
Classifier: Programming Language :: Python :: 3.12
Classifier: Topic :: Software Development
Classifier: Topic :: Scientific/Engineering
Classifier: Topic :: Scientific/Engineering :: Artificial Intelligence
Classifier: Topic :: Scientific/Engineering :: Image Recognition
Classifier: Operating System :: POSIX :: Linux
Classifier: Operating System :: MacOS
Classifier: Operating System :: Microsoft :: Windows
Requires-Python: >=3.8
License-File: LICENSE
Requires-Dist: numpy>=1.23.5
Requires-Dist: matplotlib>=3.3.0
Requires-Dist: Pillow>=7.1.2
Requires-Dist: PyYAML>=5.3.1
Requires-Dist: requests>=2.23.0
Requires-Dist: scipy>=1.4.1
Requires-Dist: psutil>=5.8.0
Requires-Dist: polars>=0.20.0
Requires-Dist: ultralytics-thop>=2.0.18
Requires-Dist: hub-sdk>=0.0.12
Provides-Extra: export
Requires-Dist: numpy<2.0.0; extra == "export"
Requires-Dist: onnx>=1.12.0; platform_system != "Darwin" and extra == "export"
Requires-Dist: onnx<1.18.0,>=1.12.0; platform_system == "Darwin" and extra == "export"
Requires-Dist: onnxslim>=0.1.82; extra == "export"
Requires-Dist: coremltools>=9.0; (platform_system != "Windows" and python_version <= "3.13") and extra == "export"
Requires-Dist: scikit-learn>=1.3.2; (platform_system != "Windows" and python_version <= "3.13") and extra == "export"
Requires-Dist: openvino>=2024.0.0; extra == "export"
Requires-Dist: tensorflow<=2.19.0,>=2.0.0; extra == "export"
Requires-Dist: tensorflowjs>=2.0.0; extra == "export"
Requires-Dist: tensorstore>=0.1.63; (platform_machine == "aarch64" and python_version >= "3.9") and extra == "export"
Requires-Dist: h5py!=3.11.0; platform_machine == "aarch64" and extra == "export"
Provides-Extra: extra
Requires-Dist: hub-sdk>=0.0.12; extra == "extra"
Requires-Dist: ipython; extra == "extra"
Requires-Dist: albumentations>=1.4.6; extra == "extra"
Requires-Dist: faster-coco-eval>=1.6.7; extra == "extra"
Provides-Extra: solutions
Requires-Dist: shapely>=2.0.0; extra == "solutions"
Requires-Dist: streamlit>=1.29.0; extra == "solutions"
Requires-Dist: flask>=3.0.1; extra == "solutions"
Provides-Extra: logging
Requires-Dist: wandb; extra == "logging"
Requires-Dist: tensorboard; extra == "logging"
Requires-Dist: mlflow; extra == "logging"
Provides-Extra: typing
Requires-Dist: scipy-stubs>=1.14.1.4; python_version >= "3.10" and extra == "typing"
Requires-Dist: types-pillow; extra == "typing"
Requires-Dist: types-psutil; extra == "typing"
Requires-Dist: types-pyyaml; extra == "typing"
Requires-Dist: types-requests; extra == "typing"
Requires-Dist: types-shapely; extra == "typing"
Dynamic: classifier
Dynamic: description
Dynamic: description-content-type
Dynamic: home-page
Dynamic: keywords
Dynamic: license
Dynamic: license-file
Dynamic: project-url
Dynamic: provides-extra
Dynamic: requires-dist
Dynamic: requires-python
Dynamic: summary
